.latest-version.generated.txt
LICENSE
README.md
pyproject.toml
src/llm2sh/__init__.py
src/llm2sh/__main__.py
src/llm2sh/cli.py
src/llm2sh/config.py
src/llm2sh/util.py
src/llm2sh.egg-info/PKG-INFO
src/llm2sh.egg-info/SOURCES.txt
src/llm2sh.egg-info/dependency_links.txt
src/llm2sh.egg-info/entry_points.txt
src/llm2sh.egg-info/requires.txt
src/llm2sh.egg-info/top_level.txt
src/llm2sh/dispatchers/AnthropicDispatcher.py
src/llm2sh/dispatchers/DefaultDispatcher.py
src/llm2sh/dispatchers/__init__.py