Metadata-Version: 2.1
Name: llm2sh
Version: 0.3.6
Summary: Ask GPT to run a command
Author-email: David Li <david@david-li.com>
License: GPL-3.0
Project-URL: Changelog, https://github.com/randombk/llm2sh/blob/master/.version
Project-URL: Source, https://github.com/randombk/llm2sh
Project-URL: Tracker, https://github.com/randombk/llm2sh/issues
Keywords: llm,gpt,cli
Requires-Python: >=3.8
License-File: LICENSE
Requires-Dist: openai>=1.30.5
Requires-Dist: anthropic
Provides-Extra: dev
Requires-Dist: build; extra == "dev"
Requires-Dist: twine; extra == "dev"
